register_value/__init__.py
register_value/_register_value.py
register_value-0.0.1.dist-info/METADATA
register_value-0.0.1.dist-info/WHEEL
register_value-0.0.1.dist-info/top_level.txt
register_value-0.0.1.dist-info/RECORD
