Metadata-Version: 2.1
Name: register-value
Version: 0.0.1
Summary: A simple global value manager
Author: Kelvin
Author-email: yan18771989297@gmail.com
